vennfig/__init__.py
vennfig/a_b.py
vennfig/and_nand.py
vennfig/complement.py
vennfig/implication.py
vennfig/mut_exclusive.py
vennfig/not_not.py
vennfig/or_nor.py
vennfig/subsets.py
vennfig/true_false.py
vennfig/venn.py
vennfig/x_not_y.py
vennfig/xor_xnor.py
vennfig-0.2.3.dist-info/LICENSE
vennfig-0.2.3.dist-info/METADATA
vennfig-0.2.3.dist-info/WHEEL
vennfig-0.2.3.dist-info/top_level.txt
vennfig-0.2.3.dist-info/RECORD
