Metadata-Version: 2.1
Name: vennfig
Version: 0.2.3
Summary: Basic Venn Diagram Figures package.
Home-page: https://github.com/shinokada/vennfig
Author: Shinichi Okada
Author-email: okada.shin@gmail.com
License: UNKNOWN
Platform: UNKNOWN
Classifier: Programming Language :: Python :: 3
Classifier: License :: OSI Approved :: MIT License
Classifier: Operating System :: OS Independent
Requires-Python: >=3.6
Requires-Dist: matplotlib
Requires-Dist: matplotlib-venn
